[
    {
        "created_at": "2020-12-06T19:14:10.000Z",
        "id": "1335663843972931587",
        "lang": "de",
        "text": "@WakanimDe Dieser Moment wenn man bei burning series die folge sehen kann obwohl bei wakanim simulcast ist xD gg"
    },
    {
        "created_at": "2020-12-06T19:11:54.000Z",
        "id": "1335663273535004672",
        "lang": "de",
        "text": "Sowohl #Wakanim-App als auch Website immer wieder offline. Selbst wenn die Seite mal l\u00e4dt, l\u00e4sst sich die aktuelle Folge nicht starten :/ #AttackOnTitan https://t.co/SZ5zIeE9SX"
    },
    {
        "created_at": "2020-12-06T19:11:33.000Z",
        "id": "1335663185186213888",
        "lang": "de",
        "text": "Heute f\u00e4ngt die finale Staffel von \u201e#AttackonTitan\u201c an!\u2694\ufe0f Sichere dir dazu jetzt dein 90 Tage #Wakanim VIP-Ticket \u00fcber unser neues #Gewinnspiel!\ud83d\ude0a -&gt;https://t.co/MVwjqMz9xX&lt;- https://t.co/RC8vFmTHpe"
    },
    {
        "created_at": "2020-12-06T19:11:01.000Z",
        "id": "1335663053141110789",
        "lang": "de",
        "text": "Kann jetzt mal bitte endlich #Wakanim gehen.\nIch will ja nicht mal AoT sehen, sondern meine anderen Serien. \ud83d\ude2a"
    },
    {
        "created_at": "2020-12-06T19:10:52.000Z",
        "id": "1335663011718180866",
        "lang": "de",
        "text": "@annaMarx23 Wakanim ist bei mir noch down"
    },
    {
        "created_at": "2020-12-06T19:10:47.000Z",
        "id": "1335662991065362433",
        "lang": "de",
        "text": "@Colin_1902 @WakanimDe Wakanim verkackt bei mir immer mehr.... w\u00fcrden sie wenigstens 3-Gatsu no Lion S1 endlich mal lizenzieren, w\u00fcrde ich Wakanim zumindest etwas verzeihen aber sie weigern sich ja mit H\u00e4nden und F\u00fc\u00dfen...."
    },
    {
        "created_at": "2020-12-06T19:10:30.000Z",
        "id": "1335662920978542592",
        "lang": "de",
        "text": "@Killutaku Bin auch sehr genervt, aber vielleicht bekommt das Wakanim in Zukunft besser hin, also w\u00fcrde ich etwas abwarten."
    },
    {
        "created_at": "2020-12-06T19:10:24.000Z",
        "id": "1335662897830256643",
        "lang": "de",
        "text": "@leo17lj @Animejutt @WakanimDe Was hat das mit Ahnung zu tun. H\u00e4tte sich wakanim die rechte mit den anderen Anbietern geteilt h\u00e4tten mittlerweile alle die Folge schon l\u00e4ngst gesehen. Aber Hauptsache noch n paar Abos abstauben (was ich nach AoT eh wieder k\u00fcndigen werde)"
    },
    {
        "created_at": "2020-12-06T19:08:26.000Z",
        "id": "1335662399710490624",
        "lang": "de",
        "text": "RT @EsLebeDerKonsum: Jetzt gerade bei Wakanim: https://t.co/Ay4ZSgsiOd"
    },
    {
        "created_at": "2020-12-06T19:07:29.000Z",
        "id": "1335662162291937281",
        "lang": "de",
        "text": "hat jemand einen vip wakanim account den er teilen k\u00f6nnte? ich w\u00fcrde gerne aot s4 gucken habe aber kein geld f\u00fcr ein abo"
    },
    {
        "created_at": "2020-12-06T19:07:11.000Z",
        "id": "1335662087817793537",
        "lang": "de",
        "text": "@Hantersob @WakanimDe Ich kannte wakanim nicht, ich dachte eigentlich dass es ein gr\u00f6\u00dferer Anbieter als AoD ist und dass es schneller geht aber es ist schon ne weile her seit dem die Folge h\u00e4tte drau\u00dfen sein m\u00fcssen und es funktioniert immer noch nicht. Motivation sinkt auch nach ner Zeit..."
    },
    {
        "created_at": "2020-12-06T19:06:45.000Z",
        "id": "1335661977235058688",
        "lang": "de",
        "text": "corona sch\u00f6n und gut aber am schlimmsten ist dass wakanim gerade down ist"
    },
    {
        "created_at": "2020-12-06T19:05:00.000Z",
        "id": "1335661535524507650",
        "lang": "de",
        "text": "@RYeager28 @WakanimDe AoD h\u00e4tte dem Ansturm sicher stand gehalten. Man hat bei denen richtig gemerkt, dass es von Folge zu Folge immer k\u00fcrzere Aussetzer gab. Aber ja, was will man von Wakanim schon erwarten?"
    },
    {
        "created_at": "2020-12-06T19:04:54.000Z",
        "id": "1335661511830855685",
        "lang": "de",
        "text": "RT @Killutaku: Riesen Katastrophe von Wakanim.\nSorry, aber wenn man sich SO einen hei\u00df erwarteten Titel sichert muss man auch gefasst sein\u2026"
    },
    {
        "created_at": "2020-12-06T19:04:25.000Z",
        "id": "1335661389008998400",
        "lang": "de",
        "text": "RT @SirZERO11: Ich: \"Darf ich AoT gucken?\"\n\nWakanim: \"Na klar!\"\n\nWakanim's Server: https://t.co/8BxZXLrEfw"
    },
    {
        "created_at": "2020-12-06T19:03:55.000Z",
        "id": "1335661265323220994",
        "lang": "de",
        "text": "Wie ich realisiere das man die erste folge von der 4 Staffel Aot nur mit einem premium account von Wakanim gucken kann https://t.co/FiOC9dDpwG"
    },
    {
        "created_at": "2020-12-06T19:03:55.000Z",
        "id": "1335661264480178176",
        "lang": "de",
        "text": "wenn das so weitergeht mache ich mir ein wakanim abo"
    },
    {
        "created_at": "2020-12-06T19:03:07.000Z",
        "id": "1335661062436352003",
        "lang": "de",
        "text": "maaaan wakanim bittee funktioniere einfachhh"
    },
    {
        "created_at": "2020-12-06T19:02:25.000Z",
        "id": "1335660888767000577",
        "lang": "de",
        "text": "Riesen Katastrophe von Wakanim.\nSorry, aber wenn man sich SO einen hei\u00df erwarteten Titel sichert muss man auch gefasst sein auf den Ansturm! Ich fands erst cool dass es eine legale Alternative gibt, werde jetzt aber vermutlich wieder k\u00fcndigen."
    },
    {
        "created_at": "2020-12-06T19:02:17.000Z",
        "id": "1335660855132819458",
        "lang": "de",
        "text": "Ich komme immer noch nicht bei Wakanim rein mannnnnnn"
    },
    {
        "created_at": "2020-12-06T19:00:58.000Z",
        "id": "1335660522579038210",
        "lang": "de",
        "text": "@Colin_1902 @WakanimDe Nope, Wakanim ist bei mir die ganze Zeit nicht erreichbar"
    },
    {
        "created_at": "2020-12-06T19:00:49.000Z",
        "id": "1335660486281613314",
        "lang": "de",
        "text": "@ihrseidbstrde wakanim vorstellung, wie aot welle die Server nicht zerst\u00f6rt und dann halt realit\u00e4t"
    },
    {
        "created_at": "2020-12-06T19:00:42.000Z",
        "id": "1335660456179019780",
        "lang": "de",
        "text": "@EdTheHeadDA auf facebook gibts schon was aber ist ohne sub, die dauern wohl noch n bisschen (wenn man halt jetzt nicht wakanim hat oder so)"
    },
    {
        "created_at": "2020-12-06T19:00:00.000Z",
        "id": "1335660279326253059",
        "lang": "de",
        "text": "@EsLebeDerKonsum Und ich kann es noch immer nicht schauen...\nRip Wakanim T.T"
    },
    {
        "created_at": "2020-12-06T18:59:29.000Z",
        "id": "1335660149780996103",
        "lang": "de",
        "text": "@beingmechris Wir warten gerade seit anderthalb Stunden dass Wakanim funktioniert"
    },
    {
        "created_at": "2020-12-06T18:58:28.000Z",
        "id": "1335659891424436224",
        "lang": "de",
        "text": "RT @kani_nara: Wakanim fdp https://t.co/QhaQwAW4pd"
    },
    {
        "created_at": "2020-12-06T18:57:56.000Z",
        "id": "1335659757898780680",
        "lang": "de",
        "text": "Aot crasht einfach wakanim xD https://t.co/Bt34bQsZQe"
    },
    {
        "created_at": "2020-12-06T18:57:51.000Z",
        "id": "1335659739523510273",
        "lang": "de",
        "text": "@MGyt09372561 @Kaizen_Anime Ich hoffe, dass \u00fcberfordert Wakanim nicht all zu sehr xD"
    },
    {
        "created_at": "2020-12-06T18:57:48.000Z",
        "id": "1335659723618734080",
        "lang": "de",
        "text": "Zu Krank die Folge 11/10\n\n#AttackonTitanFinalSeason   #WAKANIM"
    },
    {
        "created_at": "2020-12-06T18:57:13.000Z",
        "id": "1335659579254972417",
        "lang": "de",
        "text": "Wakanim beug j'en ai mahr"
    },
    {
        "created_at": "2020-12-06T18:57:03.000Z",
        "id": "1335659536330485771",
        "lang": "de",
        "text": "RT @kani_nara: Wakanim fdp https://t.co/QhaQwAW4pd"
    },
    {
        "created_at": "2020-12-06T18:56:55.000Z",
        "id": "1335659502272655361",
        "lang": "de",
        "text": "@Reijin Wakanim beug j'en mahr"
    },
    {
        "created_at": "2020-12-06T18:56:51.000Z",
        "id": "1335659484291756032",
        "lang": "de",
        "text": "RT @EsLebeDerKonsum: Jetzt gerade bei Wakanim: https://t.co/Ay4ZSgsiOd"
    },
    {
        "created_at": "2020-12-06T18:55:50.000Z",
        "id": "1335659228548247555",
        "lang": "de",
        "text": "Ich: \"Darf ich AoT gucken?\"\n\nWakanim: \"Na klar!\"\n\nWakanim's Server: https://t.co/8BxZXLrEfw"
    },
    {
        "created_at": "2020-12-06T18:55:28.000Z",
        "id": "1335659139033346052",
        "lang": "de",
        "text": "@the_beron Same \ud83d\ude02\n\nAber man sollte @WakanimDe nicht daf\u00fcr bashen im Gegenteil die machen jetzt Safe \u00dcberstunden und \u00fcberhaupt nutze Wakanim schon Jahre(!) Und es ist jetzt das erste mal so ein Problem \ud83e\udd37\ud83c\udffb\u200d\u2642\ufe0f"
    },
    {
        "created_at": "2020-12-06T18:55:07.000Z",
        "id": "1335659050256781315",
        "lang": "de",
        "text": "Jeh jetzt ist Wakanim ganz Down \ud83d\ude2d\n\nAoT crasht Wakanim \ud83d\ude05 https://t.co/tSVGMsz5LH"
    },
    {
        "created_at": "2020-12-06T18:54:56.000Z",
        "id": "1335659003985223686",
        "lang": "de",
        "text": "RT @EsLebeDerKonsum: Jetzt gerade bei Wakanim: https://t.co/Ay4ZSgsiOd"
    },
    {
        "created_at": "2020-12-06T18:53:58.000Z",
        "id": "1335658761806114817",
        "lang": "de",
        "text": "Warum l\u00e4uft eigentlich #AttackonTitanFinalSeason auf Wakanim und nicht auf Anime on Demand wie alle Staffeln zuvor? Ich glaube ich warte noch ein bissle wegen den Serverproblemen. Ich m\u00fcsste ja die ersten Episoden wegen dem Manga kennen. Aber ich kann es kaum abwarten. \ud83d\ude02"
    },
    {
        "created_at": "2020-12-06T18:53:49.000Z",
        "id": "1335658722337697797",
        "lang": "de",
        "text": "@Kaizen_Anime H\u00f6chstwahrscheinlich wegen Attack on Titan Final Season \ud83d\ude01 Wakanim hat sich nun mal damit einen Edelstein geholt"
    },
    {
        "created_at": "2020-12-06T18:51:58.000Z",
        "id": "1335658257722077184",
        "lang": "de",
        "text": "Ganz ehrlich gleich werde ich zum Titanen wen das so weiter geht, war ja absolut und gar nicht hervorsehbar das dass passiert \ud83d\ude31\ud83d\ude31\ud83d\ude18 #AttackonTitanFinalSeason #WAKANIM https://t.co/UGdXb746jc"
    },
    {
        "created_at": "2020-12-06T18:51:27.000Z",
        "id": "1335658127933444100",
        "lang": "de",
        "text": "@Mindus_ @Kenshidin Kann mich nicht einloggen  auf wakanim  xD"
    },
    {
        "created_at": "2020-12-06T18:51:06.000Z",
        "id": "1335658039400075266",
        "lang": "de",
        "text": "@Yeontansmom_ einer hat auf dc gestreamt und er hat es auf wakanim geschaut"
    },
    {
        "created_at": "2020-12-06T18:51:04.000Z",
        "id": "1335658031464534018",
        "lang": "de",
        "text": "Mir tun ja die #AttackonTitanFinalSeason Fans leid, die es wohl wegen Serverproblemen von #Wakanim nicht gucken k\u00f6nnen. Hoffentlich ist das bald behoben. https://t.co/xyHriLJUpj"
    },
    {
        "created_at": "2020-12-06T18:49:41.000Z",
        "id": "1335657681370091521",
        "lang": "de",
        "text": "@WakanimDe Bitte Wakanim n\u00e4chste Woche die Server aufstocken, das macht so keinen Spa\u00df :/"
    },
    {
        "created_at": "2020-12-06T18:48:13.000Z",
        "id": "1335657314347589635",
        "lang": "de",
        "text": "RT @kani_nara: Wakanim fdp https://t.co/QhaQwAW4pd"
    },
    {
        "created_at": "2020-12-06T18:47:29.000Z",
        "id": "1335657128879648769",
        "lang": "de",
        "text": "@txkumq neeeee ist schon gut ich schau morgen auf wakanim hahaaha"
    },
    {
        "created_at": "2020-12-06T18:47:28.000Z",
        "id": "1335657125146714113",
        "lang": "de",
        "text": "diggah was zum fick ist Wakanim bitte helft mir"
    },
    {
        "created_at": "2020-12-06T18:47:07.000Z",
        "id": "1335657035346677762",
        "lang": "de",
        "text": "RT @kani_nara: Wakanim fdp https://t.co/QhaQwAW4pd"
    },
    {
        "created_at": "2020-12-06T18:45:42.000Z",
        "id": "1335656680500162561",
        "lang": "de",
        "text": "Wakanim          kl\u00e4rt mich auf Wakanim um was geht es da??Nie geh\u00f6rt..okay ich mach mich schlau."
    },
    {
        "created_at": "2020-12-06T18:45:23.000Z",
        "id": "1335656599789166594",
        "lang": "de",
        "text": "Gehen die Wakanim Server wieder"
    },
    {
        "created_at": "2020-12-06T18:45:05.000Z",
        "id": "1335656525822648323",
        "lang": "de",
        "text": "@naitomia Laut Wakanim sind die Server komplett \u00fcberlastet. Vor einer Stunde war sogar die Website down \ud83d\ude14"
    },
    {
        "created_at": "2020-12-06T18:44:34.000Z",
        "id": "1335656396763885570",
        "lang": "de",
        "text": "Bei den ganzen kindischen Beleidigungen und Hetzereien w\u00fcrde ich den Server sogar extra lang down lassen lol #Wakanim #AttackonTitanFinalSeason https://t.co/2jekJ2L5c3"
    },
    {
        "created_at": "2020-12-06T18:44:20.000Z",
        "id": "1335656334621110273",
        "lang": "de",
        "text": "Ich habe das Gef\u00fchl, dass Wakanim grad arge Probleme hat. Ich komme zwar zur Folge, aber es l\u00e4dt sich den Wolf. Ach menno.... #LisaSchautSnKSeason4"
    },
    {
        "created_at": "2020-12-06T18:44:14.000Z",
        "id": "1335656312265437185",
        "lang": "de",
        "text": "und was hast du am Sonntag so gemacht? \noch hab stundenlang versucht mich bei Wakanim einzuloggen \nSuper Abend gehabt \ud83d\udc4c freue mich schon so auf n\u00e4chsten Sonntag \n#AttackonTitanFinalSeason #AttackOnTitan @WakanimDe"
    },
    {
        "created_at": "2020-12-06T18:42:12.000Z",
        "id": "1335655798844911619",
        "lang": "de",
        "text": "wakanim fdp"
    },
    {
        "created_at": "2020-12-06T18:41:44.000Z",
        "id": "1335655680167043072",
        "lang": "de",
        "text": "@Leikeima Wenn es wie bei AoD w\u00e4re, wo wirklich manche Sachen gar nicht richtig laufen, okay.\nAber mit Wakanim hatte ich bisher sonst keine gr\u00f6\u00dferen Probleme und sie haben ja auch noch andere gute Anime.\nDas bei einem so gro\u00dfen/gehypten Titel es zu Schwierigkeiten kommen kann ist normal."
    },
    {
        "created_at": "2020-12-06T18:41:39.000Z",
        "id": "1335655658969047040",
        "lang": "de",
        "text": "F5 F5 F5 F5 F5 F5 F5 F5 F5 F5 F5F5 FRQZE0LIOFKQ.LERFGI90KQE.RG9UEQRK?QFG.E8I0R9EFKFZEIKF0ZEI0UFK?ER9UI0GFK?.ERG0F8I?. ER908IFGK?ER.QG9F0IO @Wakanim"
    },
    {
        "created_at": "2020-12-06T18:40:57.000Z",
        "id": "1335655484972544001",
        "lang": "de",
        "text": "@maja_gkng ja ich warte seit ner stunde dass die wakanim server wieder oben sind. es sieht gar nicht gut aus heute"
    },
    {
        "created_at": "2020-12-06T18:39:56.000Z",
        "id": "1335655229271007233",
        "lang": "de",
        "text": "@_mimo525 bis jetzt glaub ich nur auf Wakanim"
    },
    {
        "created_at": "2020-12-06T18:39:22.000Z",
        "id": "1335655084483620870",
        "lang": "de",
        "text": "RT @Offnass: : 18h34 \n\n : \u00ab\u00a0Wakanim Error code 14\u00a0\u00bb https://t.co/45w6k9uCjp"
    },
    {
        "created_at": "2020-12-06T18:39:19.000Z",
        "id": "1335655072534056960",
        "lang": "de",
        "text": "achja n kleiner tipp f\u00fcr alle die wakanim haben aber aktuell nicht auf die seite kommen um die folge aot zu sehen\n\nbenutzt die mobile app da kommt ihr ohne gro\u00dfartige probleme durch und k\u00f6nnt entspannt die folge schauen"
    },
    {
        "created_at": "2020-12-06T18:39:17.000Z",
        "id": "1335655065412112386",
        "lang": "de",
        "text": "RT @Cram2a: @Wakanim @NetflixFR @SamuelEtienne Le cm de Netflix https://t.co/PJKm49Wf6M"
    },
    {
        "created_at": "2020-12-06T18:39:12.000Z",
        "id": "1335655045698883588",
        "lang": "de",
        "text": "Wenn sowas bei Wakanim wegen Aot S4 passiert was passiert dann bei der letzten Folge von OP \ud83e\udd14"
    },
    {
        "created_at": "2020-12-06T18:38:46.000Z",
        "id": "1335654934331744261",
        "lang": "de",
        "text": "RT @_Swisstendo: Haut mal ab von denn Wakanim Server! ich will AoT schauen https://t.co/8t7ChVUX0B"
    },
    {
        "created_at": "2020-12-06T18:38:43.000Z",
        "id": "1335654920733732873",
        "lang": "de",
        "text": "alter haut alle ab von wakanim ich will aot sehen @WakanimDe mein abo l\u00e4uft balt aus ich muss noch aot sehen bitte fixt es DANKE!!!"
    },
    {
        "created_at": "2020-12-06T18:37:40.000Z",
        "id": "1335654658686263296",
        "lang": "de",
        "text": "@Michael__752 GEL?? leute die wegen sowas jetz sagen sie k\u00fcndigen abo und wie schei\u00dfe doch Wakanim ist, haben den schuss nicht geh\u00f6rt."
    },
    {
        "created_at": "2020-12-06T18:36:54.000Z",
        "id": "1335654464993316877",
        "lang": "de",
        "text": "Da sch\u00e4mt man sich richtig, Teil der Animecommunity zu sein, wenn man sieht, wie die Leute \u00fcbertrieben wegen nem Delay ausrasten. Ist ja nicht so, als w\u00e4rs danach trotzdem 24/7 verf\u00fcgbar #Wakanim #AttackonTitanFinalSeason"
    },
    {
        "created_at": "2020-12-06T18:36:52.000Z",
        "id": "1335654458068529152",
        "lang": "de",
        "text": "@AnnaWuff https://t.co/ZQd3qUgL1W\nHatte wohl Gl\u00fcck, komme gerade nicht mehr auf die Seite \ud83d\ude05"
    },
    {
        "created_at": "2020-12-06T18:36:46.000Z",
        "id": "1335654432646725633",
        "lang": "de",
        "text": "RT @WakanimDe: ENDLICH. IST ES. SOWEIT! \ud83d\udd25 Heute um 18:34 Uhr erscheint die erste Folge von Attack on Titan Final Season bei Wakanim!\n\nWir k\u2026"
    },
    {
        "created_at": "2020-12-06T18:36:38.000Z",
        "id": "1335654400178745344",
        "lang": "de",
        "text": "@Wakanim fr\u00e9rot ???"
    },
    {
        "created_at": "2020-12-06T18:35:37.000Z",
        "id": "1335654140618346499",
        "lang": "de",
        "text": "RT @Kaizen_Anime: WTF\n\nWakanim geht steil https://t.co/pUHrPbbFCv"
    },
    {
        "created_at": "2020-12-06T18:35:20.000Z",
        "id": "1335654069453676554",
        "lang": "de",
        "text": "Wakanim diese schei\u00dfe bestimmt Kauf Ich premium"
    },
    {
        "created_at": "2020-12-06T18:34:55.000Z",
        "id": "1335653965443297285",
        "lang": "de",
        "text": "@huzja Bruder sage nicht vor 20 Uhr auf illegale Seiten wakanim ist aber wieder online"
    },
    {
        "created_at": "2020-12-06T18:33:44.000Z",
        "id": "1335653668054573058",
        "lang": "de",
        "text": "Toll, Attack on Titan Staffel 4 wurde vor einer Stunde released und Wakanim ist immer noch down, ist ja nicht so dass Wakanim die Exklusivrechte bei uns hat (haben sie), ich kann jetz nichtmal die paar Folgen, die ich noch im Backlog habe, schauen (die sind auch bei Wakanim)"
    },
    {
        "created_at": "2020-12-06T18:33:40.000Z",
        "id": "1335653651080212487",
        "lang": "de",
        "text": "Joooooooo, dann schau ich mir eben morgen die neue Staffel von Attack on Titan an \ud83d\ude43\nDie Server von Wakanim sind sowas von \u00fcberlastet \ud83d\ude02"
    },
    {
        "created_at": "2020-12-06T18:33:27.000Z",
        "id": "1335653595417620483",
        "lang": "de",
        "text": "Ich sage mal Rip #Wakanim ne, Aot Effekt halt xD"
    },
    {
        "created_at": "2020-12-06T18:33:11.000Z",
        "id": "1335653528451289091",
        "lang": "de",
        "text": "@georgeoderso @Raafey17 Auf wakanim kannst du es gucken aber kosten 5 Euro im Monat"
    },
    {
        "created_at": "2020-12-06T18:32:46.000Z",
        "id": "1335653426382954499",
        "lang": "de",
        "text": "@Michael__752 Ja isso. muss ja nicht zwei stunden sein aber ne halbe oder eine stunde :D\nglaube Wakanim hat auch 0 mit SO einem ansturm gerechnet :D"
    },
    {
        "created_at": "2020-12-06T18:31:57.000Z",
        "id": "1335653219134033920",
        "lang": "de",
        "text": "Schaut die Folge im Inkognito Modus bei Wakanim \n#AttackOnTitan"
    },
    {
        "created_at": "2020-12-06T18:31:35.000Z",
        "id": "1335653126662139906",
        "lang": "de",
        "text": "RT @Kaizen_Anime: WTF\n\nWakanim geht steil https://t.co/pUHrPbbFCv"
    },
    {
        "created_at": "2020-12-06T18:31:31.000Z",
        "id": "1335653111034224649",
        "lang": "de",
        "text": "Holy shit, ich hab die Folge gerade geschaut, richtig stark!!! \ud83d\ude0d #AttackonTitanFinalSeason #WAKANIM"
    },
    {
        "created_at": "2020-12-06T18:31:20.000Z",
        "id": "1335653065102385153",
        "lang": "de",
        "text": "RT @Kaizen_Anime: WTF\n\nWakanim geht steil https://t.co/pUHrPbbFCv"
    },
    {
        "created_at": "2020-12-06T18:31:10.000Z",
        "id": "1335653021611651084",
        "lang": "de",
        "text": "@Kaizen_Anime Wakanim geht wohl er down\ud83d\ude10"
    },
    {
        "created_at": "2020-12-06T18:30:58.000Z",
        "id": "1335652970336317445",
        "lang": "de",
        "text": "RT @Kaizen_Anime: WTF\n\nWakanim geht steil https://t.co/pUHrPbbFCv"
    },
    {
        "created_at": "2020-12-06T18:30:34.000Z",
        "id": "1335652872319619072",
        "lang": "de",
        "text": "wakanim du hundesohn was los bruder \ud83d\ude2d"
    },
    {
        "created_at": "2020-12-06T18:30:29.000Z",
        "id": "1335652850106589186",
        "lang": "de",
        "text": "WTF\n\nWakanim geht steil https://t.co/pUHrPbbFCv"
    },
    {
        "created_at": "2020-12-06T18:30:29.000Z",
        "id": "1335652849745874946",
        "lang": "de",
        "text": "RT @eh13yz: fermez vgl wakanim dmon vier"
    },
    {
        "created_at": "2020-12-06T18:29:11.000Z",
        "id": "1335652523584217096",
        "lang": "de",
        "text": "@68_tezel @ANTEIKU12 Wakanim ist zwar ein anderer Anbieter als AOD aber bin der Meinung das selbst bei AOD wochenlang es immer Probleme gab, das man erst nach minuten die Folge \u00fcberhaupt schauen konnte."
    },
    {
        "created_at": "2020-12-06T18:28:28.000Z",
        "id": "1335652344835547138",
        "lang": "de",
        "text": "WAKANIM ICH WILL MEIN ABO ABSCHLIESSEN LMAO \ud83d\ude02 \nEinfach kein Mensch wird heute diese Folge gucken k\u00f6nnen! #WAKANIM #AttackonTitanFinalSeason #ShingekiNoKyojin https://t.co/7v9g4Ut7Do"
    },
    {
        "created_at": "2020-12-06T18:27:27.000Z",
        "id": "1335652088521629698",
        "lang": "de",
        "text": "Ich will doch nur SNK schauen. \ud83e\udd7a #WAKANIM #AttackonTitanFinalSeason"
    },
    {
        "created_at": "2020-12-06T18:27:24.000Z",
        "id": "1335652073401151488",
        "lang": "de",
        "text": "RT @EsLebeDerKonsum: Jetzt gerade bei Wakanim: https://t.co/Ay4ZSgsiOd"
    },
    {
        "created_at": "2020-12-06T18:27:09.000Z",
        "id": "1335652012608909312",
        "lang": "de",
        "text": "Wakanim spinnt einfach wegen AoT hahaha zum Gl\u00fcck bin ich auch Manga Reader"
    },
    {
        "created_at": "2020-12-06T18:26:52.000Z",
        "id": "1335651941196685312",
        "lang": "de",
        "text": "Oh...Wakanim l\u00e4uft wieder...zumindest bei mir ^^ https://t.co/qgv9L44b1A"
    },
    {
        "created_at": "2020-12-06T18:26:45.000Z",
        "id": "1335651912759308288",
        "lang": "de",
        "text": "WAKANIM DU H0ND LASS MICH MEIN ABO ABSCHLIESSEN ES IST EINE STUNDE VERGANGEN"
    },
    {
        "created_at": "2020-12-06T18:26:34.000Z",
        "id": "1335651863807594499",
        "lang": "de",
        "text": "Dann schaue ich halt endlich mal ne Folge von #DrSTONE an auf #Crunchyroll  bis ich auf #wakanim endlich #AttackonTitanFinalSeason sehen kann \ud83d\ude42\u2764\ufe0f https://t.co/Ng5JVK06gu"
    },
    {
        "created_at": "2020-12-06T18:26:13.000Z",
        "id": "1335651775454572544",
        "lang": "de",
        "text": "@some1_knwn @WakanimDe Naja das Problem ist, dass wakanim vorgewarnt wurde. ^^ Man hatte damals schon bei AoD gesehen wie das abl\u00e4uft und seither ist das AoT-Franchise nochmal angewachsen. Also war abzusehen das es einen riesigen Sturm geben sollte und wenn man wei\u00df das es ein Problem geben wird."
    },
    {
        "created_at": "2020-12-06T18:26:12.000Z",
        "id": "1335651772673748993",
        "lang": "de",
        "text": "RT @Svensti: Bei Wakanim gerade so https://t.co/evoZBz8SMZ"
    },
    {
        "created_at": "2020-12-06T18:25:56.000Z",
        "id": "1335651704088485890",
        "lang": "de",
        "text": "@KingRauter @TheLukutakina @WakanimDe H\u00e4 nat\u00fcrlich nur ich wollte fragen ob es auch die anderen Seasons auf Wakanim gibt weil wenn du dir jede Folge kaufen magst is das verdammt teuer in ich kann\u2019s mir leider nich leisten und au\u00dferdem ich schau eh nie illegal"
    },
    {
        "created_at": "2020-12-06T18:25:48.000Z",
        "id": "1335651670630469636",
        "lang": "de",
        "text": "RT @WakanimDe: ENDLICH. IST ES. SOWEIT! \ud83d\udd25 Heute um 18:34 Uhr erscheint die erste Folge von Attack on Titan Final Season bei Wakanim!\n\nWir k\u2026"
    },
    {
        "created_at": "2020-12-06T18:25:46.000Z",
        "id": "1335651662179037184",
        "lang": "de",
        "text": "fermez vgl wakanim dmon vier"
    },
    {
        "created_at": "2020-12-06T18:25:17.000Z",
        "id": "1335651542926503937",
        "lang": "de",
        "text": "Live Schaltung zu den Servern von Wakanim: https://t.co/4Ibj6wNTZp"
    },
    {
        "created_at": "2020-12-06T18:25:00.000Z",
        "id": "1335651471879254021",
        "lang": "de",
        "text": "@einfachJessie Ich schaue nur auf Deutsch und musste deswegen schon Wakanim entfolgen, um nicht gespoilert zu werden..."
    },
    {
        "created_at": "2020-12-06T18:24:40.000Z",
        "id": "1335651388177739783",
        "lang": "de",
        "text": "@Painorinio @1oder2 hey wakanim geht mittlerweile wieder"
    },
    {
        "created_at": "2020-12-06T18:24:38.000Z",
        "id": "1335651377326911490",
        "lang": "de",
        "text": "Die #Wakanim-Server bluten?\nNicht aufgeben! \nDie Folge wird ja nicht ausverkauft sein *kappa*\n#AttackonTitanFinalSeason #AttackOnTitan https://t.co/XPTILnse3W"
    },
    {
        "created_at": "2020-12-06T18:23:19.000Z",
        "id": "1335651045599567874",
        "lang": "de",
        "text": "@Wakanim 18h34 hein https://t.co/aVVqqi3x41"
    },
    {
        "created_at": "2020-12-06T18:22:24.000Z",
        "id": "1335650817223909379",
        "lang": "de",
        "text": "RT @Svensti: Bei Wakanim gerade so https://t.co/evoZBz8SMZ"
    },
    {
        "created_at": "2020-12-06T18:21:28.000Z",
        "id": "1335650580988092423",
        "lang": "de",
        "text": "RT @einfachJessie: Ihr wartet grad auf AOT? W\u00e4hrend ihr wartet, schaut doch meinen Stream :)) (hier regen wir uns auch \u00fcber Wakanim auf)\nht\u2026"
    },
    {
        "created_at": "2020-12-06T18:21:02.000Z",
        "id": "1335650473047715840",
        "lang": "de",
        "text": "mittlerweile ist nicht nur wakanim down sondern auch alle anderen anime seiten wo man attack on titan gucken kann... hab ich geh\u00f6rt"
    },
    {
        "created_at": "2020-12-06T18:20:30.000Z",
        "id": "1335650336594386948",
        "lang": "de",
        "text": "RT @kani_nara: Wakanim fdp https://t.co/QhaQwAW4pd"
    },
    {
        "created_at": "2020-12-06T18:20:14.000Z",
        "id": "1335650269913362432",
        "lang": "de",
        "text": "@Hello_there__f @Jotarokidd wakanim dachte die sind ready f\u00fcr die aot welle aber dann ist die seite abgest\u00fcrzt"
    },
    {
        "created_at": "2020-12-06T18:20:01.000Z",
        "id": "1335650216763150336",
        "lang": "de",
        "text": "@itsyungjnf ja aber bei wakanim braucht man doch ein abo oder nicht?"
    },
    {
        "created_at": "2020-12-06T18:19:33.000Z",
        "id": "1335650098697691137",
        "lang": "de",
        "text": "@shinyfrio H\u00e4ngt alles Bro bin sogar bei wakanim nicht reingekommen"
    },
    {
        "created_at": "2020-12-06T18:18:03.000Z",
        "id": "1335649722489573376",
        "lang": "de",
        "text": "RT @kani_nara: Wakanim fdp https://t.co/QhaQwAW4pd"
    },
    {
        "created_at": "2020-12-06T18:17:35.000Z",
        "id": "1335649603874656256",
        "lang": "de",
        "text": "@SepPietsmiet @WakanimDe Ich w\u00fcrde ja sagen, viel Spa\u00df...aber Wakanim ist down. XD"
    },
    {
        "created_at": "2020-12-06T18:17:29.000Z",
        "id": "1335649580269056001",
        "lang": "de",
        "text": "RT @kani_nara: Wakanim fdp https://t.co/QhaQwAW4pd"
    },
    {
        "created_at": "2020-12-06T18:17:27.000Z",
        "id": "1335649570831937540",
        "lang": "de",
        "text": "Kann mir jemand sein Wakanim acc nur f\u00fcr heute ausleihen ? F\u00fcr AOT die neue Episode. W\u00e4re echt nice. Danke"
    },
    {
        "created_at": "2020-12-06T18:17:25.000Z",
        "id": "1335649560375545856",
        "lang": "de",
        "text": "@cloveryfn Wakanim zu heftig!"
    },
    {
        "created_at": "2020-12-06T18:17:06.000Z",
        "id": "1335649481522618372",
        "lang": "de",
        "text": "@FiruHaikyuu Da Wakanim gerade down ist wird sich da jz geg\u00f6nnt :D"
    },
    {
        "created_at": "2020-12-06T18:16:48.000Z",
        "id": "1335649407686078464",
        "lang": "de",
        "text": "@WakanimDe Genau so wie bei AoD wo am Erscheinungstag der Folgen die Seite auch zusammen brach...\n\nDachte Wakanim kriegt das besser geregelt aber... Naja"
    },
    {
        "created_at": "2020-12-06T18:16:06.000Z",
        "id": "1335649230518677504",
        "lang": "de",
        "text": "Die einzige Chance zu gucken \ud83d\ude2b #WAKANIM #waknimdown #ShingekiNoKyojin #AttackonTitanFinalSeason #AttackOnTitan @WakanimDe https://t.co/pWCoyFOWyg"
    },
    {
        "created_at": "2020-12-06T18:15:23.000Z",
        "id": "1335649051463782405",
        "lang": "de",
        "text": "@Clappysannnn @MarcelAnime L\u00e4uft ja auch nue auf Wakanim Crunchyroll hat nur die Option aber keine Folgen drin xD"
    },
    {
        "created_at": "2020-12-06T18:15:22.000Z",
        "id": "1335649045147230222",
        "lang": "de",
        "text": "@CouBlack @OzaruStones Nichtmal Wakanim hat best\u00e4tigt dass die Folgen garnicht ohne Abo zu sehen sein werden"
    },
    {
        "created_at": "2020-12-06T18:15:18.000Z",
        "id": "1335649031490576389",
        "lang": "de",
        "text": "@Linachan04 Was ist denn bei wakanim gerade?"
    },
    {
        "created_at": "2020-12-06T18:14:55.000Z",
        "id": "1335648934706999299",
        "lang": "de",
        "text": "@iYuukkii @WakanimDe Ich finde man h\u00e4tte mit so einem Ansturm rechnen k\u00f6nnen, wenn Wakanim die einzige legale deutsche Seite ist, wo man S4 schauen kann"
    },
    {
        "created_at": "2020-12-06T18:14:46.000Z",
        "id": "1335648896752758793",
        "lang": "de",
        "text": "@LeonVossi Season 4 startet und Wakanim is einf komplett \u00fcberfordert hahaha"
    },
    {
        "created_at": "2020-12-06T18:14:42.000Z",
        "id": "1335648877295382544",
        "lang": "de",
        "text": ": 18h34 \n\n : \u00ab\u00a0Wakanim Error code 14\u00a0\u00bb https://t.co/45w6k9uCjp"
    },
    {
        "created_at": "2020-12-06T18:14:38.000Z",
        "id": "1335648861755482123",
        "lang": "de",
        "text": "@MarcelAnime @ayesenpaix Ich hab aber auch wakanim kein crunchyroll"
    },
    {
        "created_at": "2020-12-06T18:14:35.000Z",
        "id": "1335648849747193857",
        "lang": "de",
        "text": "@chloeful SIE IST SCHON DAAA!!\n\nhttps://t.co/pSzespf6OH"
    },
    {
        "created_at": "2020-12-06T18:14:33.000Z",
        "id": "1335648841387962369",
        "lang": "de",
        "text": "@kingbron38 l\u00e4uft grad schon? Und m\u00fcsste \u00fcber wakanim nich gehen?"
    },
    {
        "created_at": "2020-12-06T18:14:13.000Z",
        "id": "1335648757048889347",
        "lang": "de",
        "text": "wakanim du ehrenloser h0nd"
    },
    {
        "created_at": "2020-12-06T18:12:46.000Z",
        "id": "1335648392442220550",
        "lang": "de",
        "text": "RT @kani_nara: Wakanim fdp https://t.co/QhaQwAW4pd"
    },
    {
        "created_at": "2020-12-06T18:12:41.000Z",
        "id": "1335648372930334722",
        "lang": "de",
        "text": "WAKANIM BANDE DE FDP\ud83e\udd2c\ud83e\udd2c"
    },
    {
        "created_at": "2020-12-06T18:12:19.000Z",
        "id": "1335648278910734337",
        "lang": "de",
        "text": "Warum holt sich Wakanim AoT wenn ihr Server viel zu schwach ist."
    },
    {
        "created_at": "2020-12-06T18:12:09.000Z",
        "id": "1335648235256492033",
        "lang": "de",
        "text": "@sascha922 @WakanimDe AoT killt Wakanim Server \ud83d\ude02\ud83d\ude02"
    },
    {
        "created_at": "2020-12-06T18:11:52.000Z",
        "id": "1335648164372738049",
        "lang": "de",
        "text": "Alle die auf #AOT warten und ein Bild mit ihrer IP posten, weil Wakanim down ist. https://t.co/KYQ2dvM8fl"
    },
    {
        "created_at": "2020-12-06T18:11:03.000Z",
        "id": "1335647959430672384",
        "lang": "de",
        "text": "@PixelViet @NaniAnimeTalk F5 auf wakanim blutet"
    },
    {
        "created_at": "2020-12-06T18:11:02.000Z",
        "id": "1335647954917597192",
        "lang": "de",
        "text": "Okay, beim Warten auf #AttackonTitanFinalSeason wollte ich anfangen 3-gatsu no lion zu schauen, weil ich das schon ewig vorhatte.\nMoment, wer streamt das nochmal? Ach, ja Wakanim. Mein Ersatzplan f\u00fcr einen Serverausfall war ein Serie auf dem selben Server... Big\ud83e\udde0Time"
    },
    {
        "created_at": "2020-12-06T18:10:50.000Z",
        "id": "1335647907714899969",
        "lang": "de",
        "text": "RT @kani_nara: Wakanim fdp https://t.co/QhaQwAW4pd"
    },
    {
        "created_at": "2020-12-06T18:10:33.000Z",
        "id": "1335647836227194882",
        "lang": "de",
        "text": "@Linachan04 \u00c4hm wo schaust du es bei mir crasht wakanim die ganze Zeit."
    },
    {
        "created_at": "2020-12-06T18:10:05.000Z",
        "id": "1335647716651786242",
        "lang": "de",
        "text": "Die letzte Staffel von Attack on Titan ist endlich auf Wakanim im Simulcast verf\u00fcgbar!\n\nHier zu Wakanim: https://t.co/ED9qZQdSNf https://t.co/bO2ojToGBs"
    },
    {
        "created_at": "2020-12-06T18:10:04.000Z",
        "id": "1335647712470061058",
        "lang": "de",
        "text": "Wakanim fdp https://t.co/QhaQwAW4pd"
    },
    {
        "created_at": "2020-12-06T18:09:26.000Z",
        "id": "1335647554185408515",
        "lang": "de",
        "text": "@Wakanim @Hyo_Rine BV BG"
    },
    {
        "created_at": "2020-12-06T18:09:12.000Z",
        "id": "1335647495377068035",
        "lang": "de",
        "text": "@sascha922 @WakanimDe Ich musste mich eben auch neu Einloggen und hing \u00fcber 2 Minuten im Ladebildschirm fest, wohl etwas \u00fcberlastet Wakanim heute"
    },
    {
        "created_at": "2020-12-06T18:09:11.000Z",
        "id": "1335647490796908548",
        "lang": "de",
        "text": "Ich glaube die Wakanim Seite wurde gerade von zu vielen Attack on Titan Fans gest\u00fcrmt und ist minimal gecrushed XD"
    },
    {
        "created_at": "2020-12-06T18:08:35.000Z",
        "id": "1335647338656886785",
        "lang": "de",
        "text": "@WakanimDe Da macht man sich extra ein Wakanim Abo um die neue Attack on Titan season zu gucken und dann gleich so etwas...."
    },
    {
        "created_at": "2020-12-06T18:07:53.000Z",
        "id": "1335647162571558912",
        "lang": "de",
        "text": "Ihr wartet grad auf AOT? W\u00e4hrend ihr wartet, schaut doch meinen Stream :)) (hier regen wir uns auch \u00fcber Wakanim auf)\nhttps://t.co/VIMmz6Tisi"
    },
    {
        "created_at": "2020-12-06T18:07:41.000Z",
        "id": "1335647111405297665",
        "lang": "de",
        "text": "wakanim ntr fdp"
    },
    {
        "created_at": "2020-12-06T18:07:38.000Z",
        "id": "1335647098562285568",
        "lang": "de",
        "text": "Wakanim bz ta daronne fdp"
    },
    {
        "created_at": "2020-12-06T18:05:48.000Z",
        "id": "1335646640158478336",
        "lang": "de",
        "text": "Tja. Jetzt kann ich die Website von Wakanim zwar aufrufen, aber die Folge l\u00e4dt nicht. \ud83d\ude05 Ich gucke wohl besser erstmal was auf Crunchyroll. https://t.co/rSV4PCNfqw"
    },
    {
        "created_at": "2020-12-06T18:05:41.000Z",
        "id": "1335646611653976064",
        "lang": "de",
        "text": "Bleibt mal locker Wakanim bekommt das noch hin"
    },
    {
        "created_at": "2020-12-06T18:05:24.000Z",
        "id": "1335646536764710912",
        "lang": "de",
        "text": "Lol habe aot folge 1 von staffel 4 gesehen war zu wyld und animationen beste \ud83d\ude01 aber ez sind die server down\n#aotseason4 #AttackonTitanFinalSeason #WAKANIM @WakanimDe"
    },
    {
        "created_at": "2020-12-06T18:04:44.000Z",
        "id": "1335646370435375104",
        "lang": "de",
        "text": "@OzaruStones Man kann Wakanim Abo mit Paypal bezahlen \ud83e\udd14"
    },
    {
        "created_at": "2020-12-06T18:04:40.000Z",
        "id": "1335646355369447424",
        "lang": "de",
        "text": "@Pablo_Giovanna @Wakanim Ntm fdp"
    },
    {
        "created_at": "2020-12-06T18:04:12.000Z",
        "id": "1335646234607050753",
        "lang": "de",
        "text": "OMG warte, es scheint jetzt endlich zu funktionieren!!!!! #AttackonTitanFinalSeason #WAKANIM"
    },
    {
        "created_at": "2020-12-06T18:03:59.000Z",
        "id": "1335646182585065473",
        "lang": "de",
        "text": "@tuturugaming1 Ich hab kein wakanim rip egal ich muss warten https://t.co/eTKU4RCpBo"
    },
    {
        "created_at": "2020-12-06T18:03:52.000Z",
        "id": "1335646151144566786",
        "lang": "de",
        "text": "ROTTWEILER, ASSASSINS @Wakanim WUHAAAAAAAAAAAAAAAAAAAAAAAAAAAAAAAAAN"
    },
    {
        "created_at": "2020-12-06T18:03:11.000Z",
        "id": "1335645981795344384",
        "lang": "de",
        "text": "snk wakanim j\u2019comprends rien ach had lkhra 3awtani"
    },
    {
        "created_at": "2020-12-06T18:02:42.000Z",
        "id": "1335645856729534465",
        "lang": "de",
        "text": "@WakanimDe Die armen leute bei Wakanim die einfach hyped sin die Rechte an Aot zu haben un dann von 12 J\u00e4hrigen, die keine Ahnung von Server Strukturen haben, dumm gemacht werden."
    },
    {
        "created_at": "2020-12-06T18:02:14.000Z",
        "id": "1335645741939904519",
        "lang": "de",
        "text": "Don\u2019t care about AOT aber wollt auch gleich #wakanim gucken \ud83d\ude02"
    },
    {
        "created_at": "2020-12-06T18:02:06.000Z",
        "id": "1335645706330251265",
        "lang": "de",
        "text": "@BaihuBlu @WakanimDe Ja es funktioniert bei mir n\u00e4mlich auch nicht obwohl ich Wakanim VIP hab"
    },
    {
        "created_at": "2020-12-06T18:00:43.000Z",
        "id": "1335645360509874180",
        "lang": "de",
        "text": "@Gr11Ethan @Wakanim Roh zut :("
    },
    {
        "created_at": "2020-12-06T18:00:40.000Z",
        "id": "1335645348467978242",
        "lang": "de",
        "text": "bon wakanim marche fck netflix"
    },
    {
        "created_at": "2020-12-06T18:00:35.000Z",
        "id": "1335645327228088327",
        "lang": "de",
        "text": "@WakanimDe wakanim hat den Ansturm der AoT-Liebhaber untersch\u00e4tzt. Selbst das Team von @AnimeonDemandDE musste das durchmachen!! Und yayy #wakanim trendet gerade megaaaa"
    },
    {
        "created_at": "2020-12-06T17:59:53.000Z",
        "id": "1335645151549661192",
        "lang": "de",
        "text": "wakanim du hurensohn"
    },
    {
        "created_at": "2020-12-06T17:59:35.000Z",
        "id": "1335645073833402370",
        "lang": "de",
        "text": "RT @EsLebeDerKonsum: Jetzt gerade bei Wakanim: https://t.co/Ay4ZSgsiOd"
    },
    {
        "created_at": "2020-12-06T17:59:34.000Z",
        "id": "1335645068678615042",
        "lang": "de",
        "text": "@iilham1209 wakanim les fdp"
    },
    {
        "created_at": "2020-12-06T17:59:29.000Z",
        "id": "1335645047904202753",
        "lang": "de",
        "text": "Wakanim est mort"
    },
    {
        "created_at": "2020-12-06T17:59:04.000Z",
        "id": "1335644943294083072",
        "lang": "de",
        "text": "Wenn man Attack on Titan auf Wakanim schauen m\u00f6chte und erstmal PlayStation-Vorbestell-Flashbacks hat. #wakanim"
    },
    {
        "created_at": "2020-12-06T17:58:51.000Z",
        "id": "1335644889850253312",
        "lang": "de",
        "text": "@MarcelAnime aot ist zu krass f\u00fcr wakanim"
    },
    {
        "created_at": "2020-12-06T17:57:41.000Z",
        "id": "1335644594973847552",
        "lang": "de",
        "text": "@mommopog @shiray999 Ka finde bei Haikyu ist der Dub nicht so schlecht wie bei anderen anime \nAber kann eh nicht gucken weil Wakanim down ist"
    },
    {
        "created_at": "2020-12-06T17:57:20.000Z",
        "id": "1335644508965494787",
        "lang": "de",
        "text": "@ my fellow germans\n\nchillt einfach. Wakanim arbeitet hart um uns die folge schnell und in guter qualit\u00e4t zu bringen. dass mal server down sind kann bei so einem gro\u00dfen titel passieren.\n\ngeduld ihr lieben :) https://t.co/dMWZkGPvin"
    },
    {
        "created_at": "2020-12-06T17:57:18.000Z",
        "id": "1335644501159923722",
        "lang": "de",
        "text": "@WakanimDe WAKANIM IHR SCHAFFT DAS"
    },
    {
        "created_at": "2020-12-06T17:56:58.000Z",
        "id": "1335644417080905737",
        "lang": "de",
        "text": "RT @Rayfyx: \"Error wakanim code 15\"\n\n- https://t.co/V2XBm9AYcR"
    },
    {
        "created_at": "2020-12-06T17:56:57.000Z",
        "id": "1335644412253265927",
        "lang": "de",
        "text": "RT @sief_awl: Wakanim-error code 15 https://t.co/6fLbCr5Amr"
    },
    {
        "created_at": "2020-12-06T17:56:55.000Z",
        "id": "1335644404875456518",
        "lang": "de",
        "text": "LAN BITTE FUNKTIONIER WAKANIM ICH WILL DIR SOGAR GELD IN DEN G\u00d6T STECKEN UND TROTZDEM BIST DU \u00dcBERLASTET????? DEINE MUTTER DU H0ND"
    },
    {
        "created_at": "2020-12-06T17:56:51.000Z",
        "id": "1335644388190539776",
        "lang": "de",
        "text": "@linolut0k ja deshalb ist auch jeder auf wakanim und deshalb ist wakanim auch down https://t.co/6wAdYBPyXL"
    },
    {
        "created_at": "2020-12-06T17:56:50.000Z",
        "id": "1335644383887175682",
        "lang": "de",
        "text": "RT @EsLebeDerKonsum: Jetzt gerade bei Wakanim: https://t.co/Ay4ZSgsiOd"
    },
    {
        "created_at": "2020-12-06T17:56:41.000Z",
        "id": "1335644343751815170",
        "lang": "de",
        "text": "Wakanim fdp"
    },
    {
        "created_at": "2020-12-06T17:56:07.000Z",
        "id": "1335644202873614337",
        "lang": "de",
        "text": "Aller wakanim du nerf"
    },
    {
        "created_at": "2020-12-06T17:56:02.000Z",
        "id": "1335644180517892100",
        "lang": "de",
        "text": "@semvri @WakanimDe selfhosted w\u00e4re sowas verst\u00e4ndlich aber \u00fcberleg mal wie gro\u00df der ansturm gewesen sein muss das netzwerke im gr\u00f6\u00dfen bereich von amazon, google microsoft down gehen. denn wie man am 504 lesen konnte ist wakanim hosted auf microsoft azure."
    },
    {
        "created_at": "2020-12-06T17:55:52.000Z",
        "id": "1335644140802084866",
        "lang": "de",
        "text": "wakanim funktioniert halt einfach immer noch nicht, ich schlag meinen sch\u00e4del gegen die wand"
    },
    {
        "created_at": "2020-12-06T17:55:50.000Z",
        "id": "1335644129942974465",
        "lang": "de",
        "text": "wakanim ist immernoch down...... https://t.co/x02RlRSrGp"
    },
    {
        "created_at": "2020-12-06T17:55:37.000Z",
        "id": "1335644074418851840",
        "lang": "de",
        "text": "@killuacuIt welcher mensch guckt auf wakanim animes haha"
    },
    {
        "created_at": "2020-12-06T17:55:23.000Z",
        "id": "1335644016101175300",
        "lang": "de",
        "text": "Die Server von Wakanim sind grade komplett down :( will doch nur AoT schauen PepeHands"
    },
    {
        "created_at": "2020-12-06T17:55:15.000Z",
        "id": "1335643982618038272",
        "lang": "de",
        "text": "@Kevkowichy Wir alle auf den suryer von wakanim https://t.co/a4HwEKELNY"
    },
    {
        "created_at": "2020-12-06T17:54:57.000Z",
        "id": "1335643908383133696",
        "lang": "de",
        "text": "Wakanim-error code 15 https://t.co/6fLbCr5Amr"
    },
    {
        "created_at": "2020-12-06T17:54:41.000Z",
        "id": "1335643841718865922",
        "lang": "de",
        "text": "@Kevkowichy Jedes jahr wieder... \ud83d\ude02 ob aod oder wakanim aber hey aot ist nun mal Ne \u00c4ra F\u00fcr sich\ud83d\ude0a"
    },
    {
        "created_at": "2020-12-06T17:54:40.000Z",
        "id": "1335643837902049282",
        "lang": "de",
        "text": "@w4vytear @nozoki96 Wakanim, das ist aber gerade down wegen \u00dcberlastung und du brauchst ein Abo."
    },
    {
        "created_at": "2020-12-06T17:54:22.000Z",
        "id": "1335643761825746945",
        "lang": "de",
        "text": "Da ist Wakanim auch schon \u00fcberlastet wegen der vierten Staffel von Attack in Titan..."
    },
    {
        "created_at": "2020-12-06T17:54:21.000Z",
        "id": "1335643759078494208",
        "lang": "de",
        "text": "Fucking Wakanim ist \u00fcberlastet... \nWof\u00fcr bezahl ich \u00fcberhaupt?\n\nICH WILL ATTACK ON TITAN S4!"
    },
    {
        "created_at": "2020-12-06T17:53:48.000Z",
        "id": "1335643618988716034",
        "lang": "de",
        "text": "@niquetaemort Wakanim fdp sa marche mm pas \ud83d\ude2d\ud83d\ude2d\ud83d\ude2d"
    },
    {
        "created_at": "2020-12-06T17:53:35.000Z",
        "id": "1335643565792309248",
        "lang": "de",
        "text": "Die Wakanim Server so.\n#AttackonTitanFinalSeason https://t.co/t8ouyu3jx8"
    },
    {
        "created_at": "2020-12-06T17:53:32.000Z",
        "id": "1335643552085368832",
        "lang": "de",
        "text": "@PixelViet Wakanim Server sagen nein"
    },
    {
        "created_at": "2020-12-06T17:53:26.000Z",
        "id": "1335643526110072832",
        "lang": "de",
        "text": "Wollte mir gerade #AttackonTitanFinalSeason ansehen  die #Server sind  #down  von #WAKANIM https://t.co/DkjnmWF5q7"
    },
    {
        "created_at": "2020-12-06T17:53:24.000Z",
        "id": "1335643518623158272",
        "lang": "de",
        "text": "Weshhhh wakanim rends ouf"
    },
    {
        "created_at": "2020-12-06T17:53:15.000Z",
        "id": "1335643479091908610",
        "lang": "de",
        "text": "Ich sitze hier mit ipad, Handy, pc und ps4 und versuche irgendwie in Wakanim reinzukommen\ud83d\ude02 gabs so auch noch nicht @WakanimDe #WAKANIM #AttackonTitanFinalSeason #ShingekiNoKyojin #wakanimdown"
    },
    {
        "created_at": "2020-12-06T17:52:59.000Z",
        "id": "1335643415573372928",
        "lang": "de",
        "text": "RT @martin65944947: @WakanimDe BITTTTTTTTTEEEEEEE WAKANIM WIR WOLLEN GUCKEN"
    },
    {
        "created_at": "2020-12-06T17:52:36.000Z",
        "id": "1335643316059316224",
        "lang": "de",
        "text": "#AttackonTitanFinalSeason  ist so powerful \ud83d\ude02 Wakanim ist down ok ich warte etwas \ud83d\ude44 https://t.co/XruG02BDVi"
    },
    {
        "created_at": "2020-12-06T17:52:33.000Z",
        "id": "1335643304612990979",
        "lang": "de",
        "text": "@WakanimDe @Kevkowichy Attack on Wakanim aber ganz normal"
    }
]